{
  "generated_at": "2026-05-02T11:34:50Z",
  "country": "Canada",
  "total_stories": 63,
  "categories": [
    "Diplomacy",
    "Military",
    "Energy",
    "Economy",
    "Local Events"
  ],
  "stories": [
    {
      "title": "Vaughn Palmer: There has to be a better way to resolve overlapping claims in B.C. treaty process",
      "source": "Vancouver Sun",
      "url": "https://vancouversun.com/opinion/columnists/vaughn-palmer-there-has-to-be-better-way-to-resolve-overlapping-claims-bc-treaty-process",
      "published_date": "2026-04-30T23:43:32Z",
      "category": "Diplomacy"
    },
    {
      "title": "No deal yet on Gordie Howe bridge opening, U.S. ambassador says; Windsor mayor still hopes for May",
      "source": "Windsor Star",
      "url": "https://windsorstar.com/news/local-news/no-deal-yet-on-gordie-howe-bridge-opening-u-s-ambassador-says-windsor-mayor-still-hopes-for-may",
      "published_date": "2026-04-30T19:57:37Z",
      "category": "Diplomacy"
    },
    {
      "title": "First Indigenous senator attends Saskatoon youth conference in 1962",
      "source": "The StarPhoenix",
      "url": "https://thestarphoenix.com/news/local-news/first-indigenous-senator-saskatoon-youth-conference-1962",
      "published_date": "2026-04-30T12:00:21Z",
      "category": "Diplomacy"
    },
    {
      "title": "Young workers bearing brunt of Canada's 'frozen' job market: Survey",
      "source": "Toronto Sun",
      "url": "https://torontosun.com/news/national/young-workers-feeling-brunt-job-market",
      "published_date": "2026-04-29T22:47:41Z",
      "category": "Diplomacy"
    },
    {
      "title": "IRAN WAR UPDATES: Iran proposes to reopen Strait of Hormuz without nuclear agreement",
      "source": "Toronto Sun",
      "url": "https://torontosun.com/news/world/iran-war-updates-april-27",
      "published_date": "2026-04-27T11:21:32Z",
      "category": "Diplomacy"
    },
    {
      "title": "Man running Vancouver to Ontario for $100K mental health fundraiser",
      "source": "Burns Lake District News",
      "url": "https://burnslakelakesdistrictnews.com/2026/05/01/man-running-vancouver-to-ontario-for-100k-mental-health-fundraiser/",
      "published_date": "2026-05-02T00:40:00Z",
      "category": "Military"
    },
    {
      "title": "Windsor police seek three suspects after knife threat, pepper spray attack on youths",
      "source": "Windsor Star",
      "url": "https://windsorstar.com/news/local-news/windsor-police-seek-three-suspects-after-knife-threat-pepper-spray-attack-on-youths",
      "published_date": "2026-05-01T13:06:12Z",
      "category": "Military"
    },
    {
      "title": "Canadian military won’t renew 65-year Rogers Pass avalanche control agreement",
      "source": "Burns Lake District News",
      "url": "https://burnslakelakesdistrictnews.com/2026/04/30/canadian-military-wont-renew-65-year-rogers-pass-avalanche-control-agreement/",
      "published_date": "2026-04-30T23:01:00Z",
      "category": "Military"
    },
    {
      "title": "Vancouver playwright re-examines the Israel-Palestine narrative from a soldier&#039;s view",
      "source": "Vancouver Sun",
      "url": "https://vancouversun.com/entertainment/vancouver-playwright-re-examines-the-israel-palestine-narrative-from-a-soldiers-view",
      "published_date": "2026-04-30T18:00:22Z",
      "category": "Military"
    },
    {
      "title": "IRAN WAR UPDATES: Supreme leader says Iran will protect 'nuclear and missile capabilities'",
      "source": "Toronto Sun",
      "url": "https://torontosun.com/news/world/iran-war-updates-april-30",
      "published_date": "2026-04-30T12:44:37Z",
      "category": "Military"
    },
    {
      "title": "IRAN WAR UPDATES: Talks to end war in Iran stall as economies feel impact of rising energy costs",
      "source": "Toronto Sun",
      "url": "https://torontosun.com/news/world/iran-war-updates-april-29",
      "published_date": "2026-04-29T11:30:57Z",
      "category": "Military"
    },
    {
      "title": "MANDEL: Toronto rapper who claimed self-defence sentenced to life for murder",
      "source": "Toronto Sun",
      "url": "https://torontosun.com/news/local-news/toronto-rapper-who-claimed-self-defence-is-sentenced-to-life-for-murder",
      "published_date": "2026-04-28T22:04:15Z",
      "category": "Military"
    },
    {
      "title": "Spring economic update offers more funding to military, efforts to combat hate",
      "source": "Toronto Sun",
      "url": "https://torontosun.com/news/national/new-spending-measures-federal-economic-update",
      "published_date": "2026-04-28T21:07:23Z",
      "category": "Military"
    },
    {
      "title": "IRAN WAR UPDATES: U.S. appears cold to Iranian proposal to end war without nuclear deal",
      "source": "Toronto Sun",
      "url": "https://torontosun.com/news/world/iran-war-updates-april-28",
      "published_date": "2026-04-28T11:36:06Z",
      "category": "Military"
    },
    {
      "title": "Case against ex Mountie charged with planning to aid China called &#039;purely circumstantial&#039;",
      "source": "Vancouver Sun",
      "url": "https://vancouversun.com/news/case-against-ex-mountie-charged-planning-to-aid-china-called-purely-circumstantial",
      "published_date": "2026-04-27T23:55:53Z",
      "category": "Military"
    },
    {
      "title": "Vaughn Palmer: Polarizing B.C. Conservative leadership candidates battle at their own expense",
      "source": "Vancouver Sun",
      "url": "https://vancouversun.com/opinion/columnists/vaughn-palmer-polarizing-bc-conservative-leadership-candidates-battle-debate",
      "published_date": "2026-04-27T23:12:50Z",
      "category": "Military"
    },
    {
      "title": "Peel cops seek 4 attempted murder suspects; Ajax girl, 13, faces weapon charge",
      "source": "Toronto Sun",
      "url": "https://torontosun.com/news/crime/peel-cops-seek-4-attempted-murder-suspects",
      "published_date": "2026-04-27T21:52:05Z",
      "category": "Military"
    },
    {
      "title": "IRAN WAR UPDATES: Iran wants Strait of Hormuz reopening tied to U.S. ending the war, officials say",
      "source": "Toronto Sun",
      "url": "https://torontosun.com/news/world/iran-war-updates-april-27",
      "published_date": "2026-04-27T11:21:32Z",
      "category": "Military"
    },
    {
      "title": "IRAN WAR LATEST: Iranian official returning to Pakistan as Trump says talks to resume over phone",
      "source": "Toronto Sun",
      "url": "https://torontosun.com/news/world/iran-war-latest-iranian-official-returns-to-pakistan",
      "published_date": "2026-04-26T19:41:05Z",
      "category": "Military"
    },
    {
      "title": "HANSON: All the dream houses of the Left",
      "source": "Toronto Sun",
      "url": "https://torontosun.com/opinion/columnists/all-the-dream-houses-of-the-left",
      "published_date": "2026-04-26T15:00:45Z",
      "category": "Military"
    },
    {
      "title": "&#039;The way of the future&#039;: Goodbye guns, hello avalanche-exploding drones at Whistler",
      "source": "Vancouver Sun",
      "url": "https://vancouversun.com/news/avalanche-exploding-drones-whistler",
      "published_date": "2026-04-26T13:00:59Z",
      "category": "Military"
    },
    {
      "title": "B.C. climate news: Scientists link grey whale deaths in B.C., U.S to warming ocean &#124; Increased water storage, added filtration among Metro Vancouver plans to combat climate risks &#124; Cheap batteries take over world&#039;s power grids",
      "source": "Vancouver Sun",
      "url": "https://vancouversun.com/news/climate-change-news-to-april-26-26",
      "published_date": "2026-04-25T18:50:12Z",
      "category": "Military"
    },
    {
      "title": "B.C. court being asked to throw out approval of $12-billion natural gas pipeline",
      "source": "Vancouver Sun",
      "url": "https://vancouversun.com/business/bc-court-asked-throw-out-approval-12-billion-natural-gas-pipeline",
      "published_date": "2026-04-28T00:13:04Z",
      "category": "Energy"
    },
    {
      "title": "‘Great turnout’ – Windsor celebrates Earth Day with family fun at Malden Park",
      "source": "Windsor Star",
      "url": "https://windsorstar.com/news/local-news/great-turnout-windsor-celebrates-earth-day-with-family-fun-at-malden-park",
      "published_date": "2026-04-27T18:39:41Z",
      "category": "Energy"
    },
    {
      "title": "B.C. First Nations coalition calls for reversal of Trudeau-era salmon pen ban",
      "source": "Burns Lake District News",
      "url": "https://burnslakelakesdistrictnews.com/2026/05/02/b-c-first-nations-coalition-calls-for-reversal-of-trudeau-era-salmon-pen-ban/",
      "published_date": "2026-05-02T11:30:00Z",
      "category": "Economy"
    },
    {
      "title": "LILLEY: Toronto normalizing open drug use as taxpayers pick up tab",
      "source": "Toronto Sun",
      "url": "https://torontosun.com/opinion/columnists/toronto-olivia-chow-normalize-open-drug-use-taxpayers-pay",
      "published_date": "2026-05-01T22:41:37Z",
      "category": "Economy"
    },
    {
      "title": "B.C. forests minister unveils new federal grant, says aid needs could reach $6B",
      "source": "Burns Lake District News",
      "url": "https://burnslakelakesdistrictnews.com/2026/05/01/b-c-forests-minister-unveils-new-federal-grant-says-aid-needs-could-reach-6b/",
      "published_date": "2026-05-01T22:18:00Z",
      "category": "Economy"
    },
    {
      "title": "LAU: Toronto’s empty home tax a punitive policy that doesn’t even work",
      "source": "Toronto Sun",
      "url": "https://torontosun.com/opinion/columnists/toronto-empty-home-tax-punitive-policy-doesnt-work",
      "published_date": "2026-05-01T20:56:21Z",
      "category": "Economy"
    },
    {
      "title": "Opinion: Food security starts with protecting Ontario’s disappearing farmland",
      "source": "Windsor Star",
      "url": "https://windsorstar.com/opinion/columnists/opinion-food-security-starts-with-protecting-ontarios-disappearing-farmland",
      "published_date": "2026-05-01T11:30:15Z",
      "category": "Economy"
    },
    {
      "title": "‘Just tell us’: B.C. Jobs Minister calls for transparency about Vancouver Whitecaps bid",
      "source": "Burns Lake District News",
      "url": "https://burnslakelakesdistrictnews.com/2026/04/30/just-tell-us-b-c-jobs-minister-calls-for-transparency-about-vancouver-whitecaps-bid/",
      "published_date": "2026-04-30T21:42:00Z",
      "category": "Economy"
    },
    {
      "title": "B.C. nurses could be striking in May after talks reach an impasse",
      "source": "Vancouver Sun",
      "url": "https://vancouversun.com/news/bc-nurses-could-be-striking-may-talks-reach-impasse",
      "published_date": "2026-04-29T23:26:10Z",
      "category": "Economy"
    },
    {
      "title": "Opinion: Nation-building isn&#039;t an investment strategy",
      "source": "Vancouver Sun",
      "url": "https://vancouversun.com/opinion/op-ed/opinion-nation-building-isnt-an-investment-strategy",
      "published_date": "2026-04-29T19:30:19Z",
      "category": "Economy"
    },
    {
      "title": "‘We want to see the Whitecaps stay’ says B.C. jobs minister amid relocation report",
      "source": "Burns Lake District News",
      "url": "https://burnslakelakesdistrictnews.com/2026/04/28/we-want-to-see-the-whitecaps-stay-says-b-c-jobs-minister-amid-relocation-report/",
      "published_date": "2026-04-28T22:52:00Z",
      "category": "Economy"
    },
    {
      "title": "King calls for renewed U.S.-U.K. alliance in visit to Washington",
      "source": "Toronto Sun",
      "url": "https://torontosun.com/news/world/king-calls-for-renewed-u-s-u-k-alliance-in-visit-to-washington",
      "published_date": "2026-04-28T21:42:57Z",
      "category": "Economy"
    },
    {
      "title": "Mark Carney Liberals trumpet Canada's 'resilient' economy in spring update",
      "source": "Toronto Sun",
      "url": "https://torontosun.com/news/national/government-to-unveil-spring-economic-update",
      "published_date": "2026-04-28T14:35:49Z",
      "category": "Economy"
    },
    {
      "title": "Mark Carney's non-U.S. exports target far-fetched: Fraser Institute",
      "source": "Toronto Sun",
      "url": "https://torontosun.com/news/national/mark-carneys-non-us-exports-target-far-fetched-report",
      "published_date": "2026-04-28T09:00:53Z",
      "category": "Economy"
    },
    {
      "title": "LILLEY: Mark Carney's new Sovereign Wealth Fund just like all other funds",
      "source": "Toronto Sun",
      "url": "https://torontosun.com/opinion/columnists/mark-carneys-new-sovereign-wealth-fund-is-just-like-all-the-other-funds",
      "published_date": "2026-04-27T22:34:48Z",
      "category": "Economy"
    },
    {
      "title": "Opinion: In this uncertain time, is B.C. putting CleanBC, our best tool, back on the shelf?",
      "source": "Vancouver Sun",
      "url": "https://vancouversun.com/opinion/op-ed/opinion-in-this-uncertain-time-is-b-c-putting-cleanbc-our-best-tool-back-on-the-shelf",
      "published_date": "2026-04-27T21:00:17Z",
      "category": "Economy"
    },
    {
      "title": "Windsor MP urges Ottawa to act fast as industry reels from U.S. tariffs",
      "source": "Windsor Star",
      "url": "https://windsorstar.com/news/local-news/windsor-mp-urges-ottawa-to-act-fast-as-industry-reels-from-u-s-tariffs",
      "published_date": "2026-04-27T18:16:21Z",
      "category": "Economy"
    },
    {
      "title": "Pierre Poilievre calls for end to 'credit card budgeting' ahead of spring fiscal update",
      "source": "Toronto Sun",
      "url": "https://torontosun.com/news/national/pierre-poilievre-demands-end-credit-card-budgeting",
      "published_date": "2026-04-27T00:51:41Z",
      "category": "Economy"
    },
    {
      "title": "Should Vancouver relax short-term rental rules during World Cup to counter soaring hotel rates?",
      "source": "Vancouver Sun",
      "url": "https://vancouversun.com/news/should-vancouver-relax-short-term-rental-rules-world-cup-counter-hotel-rates",
      "published_date": "2026-04-26T13:00:29Z",
      "category": "Economy"
    },
    {
      "title": "Opinion: Why the most important food prices are rising again",
      "source": "The StarPhoenix",
      "url": "https://thestarphoenix.com/opinion/opinion-why-the-most-important-food-prices-are-rising-again",
      "published_date": "2026-04-25T13:30:30Z",
      "category": "Economy"
    },
    {
      "title": "Affordibility impoves for most Northern B.C. communities",
      "source": "Burns Lake District News",
      "url": "https://burnslakelakesdistrictnews.com/2026/04/25/affordibility-impoves-for-most-northern-b-c-communities/",
      "published_date": "2026-04-25T12:30:00Z",
      "category": "Economy"
    },
    {
      "title": "Spitfires' season comes to a screeching end after OT loss to Rangers",
      "source": "Windsor Star",
      "url": "https://windsorstar.com/sports/spitfires-season-comes-to-a-screetching-end-after-ot-loss-to-rangers",
      "published_date": "2026-05-02T04:14:52Z",
      "category": "Local Events"
    },
    {
      "title": "Driver arrested after pedestrian injured in Abbotsford crash",
      "source": "Vancouver Sun",
      "url": "https://vancouversun.com/news/local-news/driver-arrested-after-pedestrian-injured-in-abbotsford-crash",
      "published_date": "2026-05-02T02:07:51Z",
      "category": "Local Events"
    },
    {
      "title": "WARMINGTON: 'Hank Idsinga effect' has police board probing and Toronto cops making more arrests",
      "source": "Toronto Sun",
      "url": "https://torontosun.com/news/local-news/hank-idsinga-toronto-police-board-probing-antisemetism-racism",
      "published_date": "2026-05-02T00:32:57Z",
      "category": "Local Events"
    },
    {
      "title": "TTC plagued by ‘gremlins’ weeks before World Cup",
      "source": "Toronto Sun",
      "url": "https://torontosun.com/news/local-news/ttc-subway-service-disruptions-gremlins-world-cup-soccer",
      "published_date": "2026-05-01T23:50:39Z",
      "category": "Local Events"
    },
    {
      "title": "Vaughn Palmer: Projects look cancelled, despite NDP insisting they&#039;re &#039;re-paced&#039;",
      "source": "Vancouver Sun",
      "url": "https://vancouversun.com/opinion/columnists/vaughn-palmer-projects-look-cancelled-despite-ndp-insisting-otherwise",
      "published_date": "2026-05-01T23:02:57Z",
      "category": "Local Events"
    },
    {
      "title": "Letters to The Sun: City&#039;s array of parking meters is fraught with inconsistency and confusion",
      "source": "Vancouver Sun",
      "url": "https://vancouversun.com/opinion/letters/letters-to-the-sun-citys-array-of-parking-meters-is-fraught-with-inconsistency-and-confusion",
      "published_date": "2026-05-01T23:00:49Z",
      "category": "Local Events"
    },
    {
      "title": "Behchoko, NWT remains on lockdown after alleged shooting, 1 suspect at large",
      "source": "Burns Lake District News",
      "url": "https://burnslakelakesdistrictnews.com/2026/05/01/behchoko-nwt-remains-on-lockdown-after-alleged-shooting-1-suspect-at-large/",
      "published_date": "2026-05-01T22:34:00Z",
      "category": "Local Events"
    },
    {
      "title": "LILLEY: Chief Justice Wagner refuses recusal in Freedom Convoy case",
      "source": "Toronto Sun",
      "url": "https://torontosun.com/opinion/columnists/chief-justice-wagner-refuses-recusal-freedom-convoy-case-emergencies-act",
      "published_date": "2026-05-01T22:11:17Z",
      "category": "Local Events"
    },
    {
      "title": "B.C. FOI complaints surge as AI tools drive more review requests",
      "source": "Burns Lake District News",
      "url": "https://burnslakelakesdistrictnews.com/2026/05/01/b-c-foi-complaints-surge-as-ai-tools-drive-more-review-requests/",
      "published_date": "2026-05-01T22:00:00Z",
      "category": "Local Events"
    },
    {
      "title": "Vancouver park board restores lifeguards to most beaches",
      "source": "Vancouver Sun",
      "url": "https://vancouversun.com/news/local-news/vancouver-park-board-restores-lifeguards-most-beaches",
      "published_date": "2026-05-01T21:48:20Z",
      "category": "Local Events"
    },
    {
      "title": "Spirit Airlines prepares to shut down over spiraling costs, debt",
      "source": "Toronto Sun",
      "url": "https://torontosun.com/news/world/spirit-airlines-shut-down-spiraling-costs-debt",
      "published_date": "2026-05-01T21:47:05Z",
      "category": "Local Events"
    },
    {
      "title": "Man, 19, killed inside Hamilton apartment in targeted shooting: Cops",
      "source": "Toronto Sun",
      "url": "https://torontosun.com/news/local-news/hamilton-man-killed-targeted-shooting",
      "published_date": "2026-05-01T21:36:40Z",
      "category": "Local Events"
    },
    {
      "title": "City’s 'VIP' emergency chiefs in stadium for World Series and Taylor Swift",
      "source": "Toronto Sun",
      "url": "https://torontosun.com/news/local-news/toronto-emergency-chiefs-world-series-jays-taylor-swift",
      "published_date": "2026-05-01T21:20:42Z",
      "category": "Local Events"
    },
    {
      "title": "Vancouver park board staff recommend easing tree maintenance policy",
      "source": "Vancouver Sun",
      "url": "https://vancouversun.com/news/vancouver-park-board-staff-recommend-easing-tree-maintenance-policy",
      "published_date": "2026-05-01T21:10:29Z",
      "category": "Local Events"
    },
    {
      "title": "Scheduled criminal trials at 11 B.C. courthouses may not be able to proceed",
      "source": "Burns Lake District News",
      "url": "https://burnslakelakesdistrictnews.com/2026/05/01/scheduled-criminal-trials-at-11-b-c-courthouses-may-not-be-able-to-proceed/",
      "published_date": "2026-05-01T21:06:00Z",
      "category": "Local Events"
    },
    {
      "title": "First Ave. Link bus system pause: Downtown BID, councillor hopeful for 'clear, practical' clarification",
      "source": "The StarPhoenix",
      "url": "https://thestarphoenix.com/news/local-news/first-ave-link-bus-system-pause-downtown-bid-councillor-hopeful-for-clear-practical-clarification",
      "published_date": "2026-05-01T21:05:11Z",
      "category": "Local Events"
    },
    {
      "title": "Bulls and Bears: How the Whitecaps, FIFA congress dominated news this week",
      "source": "Vancouver Sun",
      "url": "https://vancouversun.com/sports/soccer/mls/vancouver-whitecaps/bulls-and-bears-how-the-whitecaps-fifa-congress-dominated-news-this-week",
      "published_date": "2026-05-01T20:58:37Z",
      "category": "Local Events"
    },
    {
      "title": "Court finds B.C.’s Legal Professions Act is not beyond government’s powers",
      "source": "Burns Lake District News",
      "url": "https://burnslakelakesdistrictnews.com/2026/05/01/court-finds-b-c-s-legal-professions-act-is-not-beyond-governments-powers/",
      "published_date": "2026-05-01T20:45:00Z",
      "category": "Local Events"
    },
    {
      "title": "Queen rocker Brian May banned from planting daffodils in his village",
      "source": "Toronto Sun",
      "url": "https://torontosun.com/news/world/queen-rocker-brian-may-banned-planting-daffodils-village-england",
      "published_date": "2026-05-01T20:38:08Z",
      "category": "Local Events"
    },
    {
      "title": "Vehicle owners can't locate missing tires after Thornhill auto shop closes",
      "source": "Toronto Sun",
      "url": "https://torontosun.com/news/local-news/customers-missing-tires-thornhill-auto-shop",
      "published_date": "2026-05-01T20:26:16Z",
      "category": "Local Events"
    }
  ]
}